jce/__init__.py
jce/__main__.py
jce/jce.py
json_csv_combiner-0.1.2.dist-info/LICENSE
json_csv_combiner-0.1.2.dist-info/METADATA
json_csv_combiner-0.1.2.dist-info/WHEEL
json_csv_combiner-0.1.2.dist-info/top_level.txt
json_csv_combiner-0.1.2.dist-info/RECORD
