Metadata-Version: 2.1
Name: json-csv-combiner
Version: 0.1.2
Summary: Combine multiple JSON/CSV/EXCEL into single file
Home-page: https://github.com/falcon-head/json-csv-combiner
Author: Shrikrishna Joisa
Author-email: shrikrishnajois@gmail.com
License: MIT
Platform: Any
Classifier: Development Status :: 3 - Alpha
Classifier: License :: OSI Approved :: MIT License
Classifier: Operating System :: OS Independent
Classifier: Programming Language :: Python
Requires-Dist: pandas
Requires-Dist: tqdm
